grobid_client/__init__.py
grobid_client/client.py
grobid_client/grobid_client.py
grobid_client_python_test-0.0.11.dist-info/LICENSE
grobid_client_python_test-0.0.11.dist-info/METADATA
grobid_client_python_test-0.0.11.dist-info/WHEEL
grobid_client_python_test-0.0.11.dist-info/entry_points.txt
grobid_client_python_test-0.0.11.dist-info/top_level.txt
grobid_client_python_test-0.0.11.dist-info/RECORD
