Metadata-Version: 2.1
Name: grobid-client-python-test
Version: 0.0.11
Summary: Simple python client for GROBID REST services
Author-email: Patrice Lopez <patrice.lopez@science-miner.com>
Maintainer-email: Patrice Lopez <patrice.lopez@science-miner.com>, Luca Foppiano <lucanoro@duck.com>
License: 
Project-URL: Homepage, https://github.com/kermitt2/grobid_client_python
Project-URL: Repository, https://github.com/kermitt2/grobid_client_python
Project-URL: Changelog, https://github.com/kermitt2/grobid_client_python
License-File: LICENSE
Requires-Dist: requests
